provable_sdk/__init__.py
provable_sdk/api.py
provable_sdk/config.py
provable_sdk/hash.py
provable_sdk/lightnet.py
provable_sdk/prove.py
provable_sdk/types.py
provable_sdk/verify.py
provable_sdk-0.0.4.dist-info/METADATA
provable_sdk-0.0.4.dist-info/WHEEL
provable_sdk-0.0.4.dist-info/top_level.txt
provable_sdk-0.0.4.dist-info/RECORD
