Metadata-Version: 2.4
Name: provable-sdk
Version: 0.0.4
Summary: Provable SDK for Python
Author: Provable
License: MIT
Project-URL: Homepage, https://github.com/provable/provable-sdk
Keywords: provable,kayros,keccak256,hash,blockchain
Requires-Python: >=3.8
Requires-Dist: pycryptodome>=3.18.0
Requires-Dist: requests>=2.31.0
Provides-Extra: dev
Requires-Dist: pytest>=7.4.0; extra == "dev"
Requires-Dist: pytest-cov>=4.1.0; extra == "dev"
